simpleFiles/__init__.py
simpleFiles/betterFileSystem.py
simpleFiles-1.1.0.dist-info/METADATA
simpleFiles-1.1.0.dist-info/WHEEL
simpleFiles-1.1.0.dist-info/top_level.txt
simpleFiles-1.1.0.dist-info/RECORD
